defsent/__init__.py
defsent/model.py
defsent/pooling.py
defsent-0.1.0.dist-info/WHEEL
defsent-0.1.0.dist-info/METADATA
defsent-0.1.0.dist-info/RECORD
