Metadata-Version: 2.1
Name: defsent
Version: 0.1.0
Summary: DefSent: Sentence Embeddings using Definition Sentences
Home-page: https://arxiv.org/abs/2105.04339
Author: hppRC
Author-email: hpp.ricecake@gmail.com
Requires-Python: >=3.7,<4.0
Classifier: Programming Language :: Python :: 3
Classifier: Programming Language :: Python :: 3.7
Classifier: Programming Language :: Python :: 3.8
Classifier: Programming Language :: Python :: 3.9
Requires-Dist: torch
Requires-Dist: transformers
Project-URL: Repository, https://github.com/hppRC/defsent
